{
  "display": "d9eb899fd1dc7df48a3f45197426fd5d",
  "baseId": "BananaFarm",
  "cost": 1250.0,
  "radius": 15.0,
  "radiusSquared": 225.0,
  "range": 40.0,
  "ignoreBlockers": false,
  "isGlobalRange": false,
  "tier": 5,
  "tiers": [
    1,
    0,
    5
  ],
  "towerSet": "Support",
  "areaTypes": [
    2
  ],
  "icon": {
    "GUID": "MonkeyIcons[BananaFarmIcon]",
    "IsValid": true
  },
  "portrait": {
    "GUID": "7a2163c9c78222549809e66926389a21",
    "IsValid": true
  },
  "instaIcon": {
    "GUID": "0dd3f49d0f34c4d91aca20d4fe25a566",
    "IsValid": true
  },
  "mods": [
    {
      "mod": "FlatPackBuildings",
      "target": "",
      "name": "BananaFarmUpgrades",
      "ImplementationType": null
    },
    {
      "mod": "FarmSubsidy",
      "target": "",
      "name": "BananaFarmUpgrades",
      "ImplementationType": null
    },
    {
      "mod": "GlobalAbilityCooldowns",
      "target": "",
      "name": "BananaFarmUpgrades",
      "ImplementationType": null
    },
    {
      "mod": "VeteranMonkeyTraining",
      "target": "",
      "name": "BananaFarmUpgrades",
      "ImplementationType": null
    },
    {
      "mod": "BetterSellDeals",
      "target": "",
      "name": "BananaFarmUpgrades",
      "ImplementationType": null
    },
    {
      "mod": "MonkeyEducation",
      "target": "",
      "name": "BananaFarmUpgrades",
      "ImplementationType": null
    },
    {
      "mod": "HealthyBananas",
      "target": "",
      "name": "BananaFarmUpgrades",
      "ImplementationType": null
    }
  ],
  "ignoreTowerForSelection": false,
  "behaviors": [
    {
      "effectModel": {
        "assetId": "d36f0ba5351201f45b62cbe9e926c48d",
        "scale": 1.0,
        "lifespan": 6.0,
        "fullscreen": false,
        "useCenterPosition": false,
        "useTransformPosition": false,
        "useTransfromRotation": false,
        "destroyOnTransformDestroy": false,
        "alwaysUseAge": false,
        "useRoundTime": false,
        "name": "EffectModel_",
        "ImplementationType": null
      },
      "name": "CreateEffectOnPlaceModel_BananaFarm-105",
      "ImplementationType": "Assets.Scripts.Simulation.Towers.Behaviors.CreateEffectOnPlace, Assembly-CSharp, Version=0.0.0.0, Culture=neutral, PublicKeyToken=null"
    },
    {
      "sound": {
        "assetId": "23a777b9950195f4f8f4bf745ef84031",
        "name": "SoundModel_UpgradeSound",
        "ImplementationType": null
      },
      "sound1": {
        "assetId": "23a777b9950195f4f8f4bf745ef84031",
        "name": "SoundModel_UpgradeSound",
        "ImplementationType": null
      },
      "sound2": {
        "assetId": "23a777b9950195f4f8f4bf745ef84031",
        "name": "SoundModel_UpgradeSound",
        "ImplementationType": null
      },
      "sound3": {
        "assetId": "23a777b9950195f4f8f4bf745ef84031",
        "name": "SoundModel_UpgradeSound",
        "ImplementationType": null
      },
      "sound4": {
        "assetId": "23a777b9950195f4f8f4bf745ef84031",
        "name": "SoundModel_UpgradeSound",
        "ImplementationType": null
      },
      "sound5": {
        "assetId": "23a777b9950195f4f8f4bf745ef84031",
        "name": "SoundModel_UpgradeSound",
        "ImplementationType": null
      },
      "sound6": {
        "assetId": "23a777b9950195f4f8f4bf745ef84031",
        "name": "SoundModel_UpgradeSound",
        "ImplementationType": null
      },
      "sound7": {
        "assetId": "23a777b9950195f4f8f4bf745ef84031",
        "name": "SoundModel_UpgradeSound",
        "ImplementationType": null
      },
      "sound8": {
        "assetId": "23a777b9950195f4f8f4bf745ef84031",
        "name": "SoundModel_UpgradeSound",
        "ImplementationType": null
      },
      "name": "CreateSoundOnUpgradeModel_BananaFarm-105",
      "ImplementationType": "Assets.Scripts.Simulation.Towers.Behaviors.CreateSoundOnUpgrade, Assembly-CSharp, Version=0.0.0.0, Culture=neutral, PublicKeyToken=null"
    },
    {
      "sound": {
        "assetId": "df4c691ccf8a3c7408ed6f156740c8b7",
        "name": "SoundModel_SellSound",
        "ImplementationType": null
      },
      "name": "CreateSoundOnSellModel_BananaFarm-105",
      "ImplementationType": "Assets.Scripts.Simulation.Towers.Behaviors.CreateSoundOnSell, Assembly-CSharp, Version=0.0.0.0, Culture=neutral, PublicKeyToken=null"
    },
    {
      "xWidth": 30.0,
      "yWidth": 30.0,
      "doesntBlockTowerPlacement": false,
      "ignoresPlacementCheck": false,
      "ignoresTowerOverlap": false,
      "name": "RectangleFootprintModel_",
      "ImplementationType": "Assets.Scripts.Simulation.Towers.Behaviors.RectangleFootprint, Assembly-CSharp, Version=0.0.0.0, Culture=neutral, PublicKeyToken=null"
    },
    {
      "effectModel": {
        "assetId": "b1dec8a8d79593843bc2e2410eae944e",
        "scale": 1.0,
        "lifespan": 1.0,
        "fullscreen": false,
        "useCenterPosition": false,
        "useTransformPosition": false,
        "useTransfromRotation": false,
        "destroyOnTransformDestroy": false,
        "alwaysUseAge": false,
        "useRoundTime": false,
        "name": "EffectModel_SellEffect",
        "ImplementationType": null
      },
      "name": "CreateEffectOnSellModel_BananaFarm-105",
      "ImplementationType": "Assets.Scripts.Simulation.Towers.Behaviors.CreateEffectOnSell, Assembly-CSharp, Version=0.0.0.0, Culture=neutral, PublicKeyToken=null"
    },
    {
      "name": "ShowCashIconInsteadModel_BananaFarm-105",
      "ImplementationType": "Assets.Scripts.Simulation.Towers.Behaviors.ShowCashIconInstead, Assembly-CSharp, Version=0.0.0.0, Culture=neutral, PublicKeyToken=null"
    },
    {
      "sound1": {
        "assetId": "564ed9d9a54a58c4fa568dc5a2155ffe",
        "name": "SoundModel_PlaceBananaFarm01",
        "ImplementationType": null
      },
      "sound2": {
        "assetId": "c2cee210faaf2b64f963003be9ac0aa6",
        "name": "SoundModel_PlaceBananaFarm02",
        "ImplementationType": null
      },
      "heroSound1": {
        "assetId": "",
        "name": "BlankSoundModel_",
        "ImplementationType": null
      },
      "heroSound2": {
        "assetId": "",
        "name": "BlankSoundModel_",
        "ImplementationType": null
      },
      "name": "CreateSoundOnTowerPlaceModel_BananaFarm-105",
      "ImplementationType": "Assets.Scripts.Simulation.Towers.Behaviors.CreateSoundOnTowerPlace, Assembly-CSharp, Version=0.0.0.0, Culture=neutral, PublicKeyToken=null"
    },
    {
      "effectModel": {
        "assetId": "823809b31a6cbab4cab5efc530f919f7",
        "scale": 1.0,
        "lifespan": 6.0,
        "fullscreen": false,
        "useCenterPosition": false,
        "useTransformPosition": false,
        "useTransfromRotation": false,
        "destroyOnTransformDestroy": false,
        "alwaysUseAge": false,
        "useRoundTime": false,
        "name": "EffectModel_UpgradeEffectTier5",
        "ImplementationType": null
      },
      "name": "CreateEffectOnUpgradeModel_BananaFarm-105",
      "ImplementationType": "Assets.Scripts.Simulation.Towers.Behaviors.CreateEffectOnUpgrade, Assembly-CSharp, Version=0.0.0.0, Culture=neutral, PublicKeyToken=null"
    },
    {
      "weapons": [
        {
          "animation": 1,
          "animationOffset": 0.0,
          "animationOffsetFrames": 0,
          "emission": {
            "offset": 0.0,
            "behaviors": null,
            "name": "SingleEmmisionTowardsTargetModel_",
            "ImplementationType": "Assets.Scripts.Simulation.Towers.Emissions.SingleEmmisionTowardsTarget, Assembly-CSharp, Version=0.0.0.0, Culture=neutral, PublicKeyToken=null"
          },
          "ejectX": 0.0,
          "ejectY": 0.0,
          "ejectZ": 23.2,
          "projectile": {
            "display": "ea93504240deadd41aed8f22737322c9",
            "id": "Projectile",
            "maxPierce": 0.0,
            "pierce": 9999999.0,
            "scale": 1.0,
            "ignoreBlockers": true,
            "usePointCollisionWithBloons": false,
            "canCollisionBeBlockedByMapLos": false,
            "filters": null,
            "behaviors": [
              {
                "minimum": 70.0,
                "maximum": 70.0,
                "bonusMultiplier": 0.0,
                "salvage": 1.0,
                "noTransformCash": false,
                "distributeSalvage": false,
                "collisionPass": 0,
                "name": "CashModel_",
                "ImplementationType": "Assets.Scripts.Simulation.Towers.Projectiles.Behaviors.Cash, Assembly-CSharp, Version=0.0.0.0, Culture=neutral, PublicKeyToken=null"
              },
              {
                "rounds": 9999999,
                "lifespanFrames": 0,
                "useRoundTime": false,
                "endOfRoundClearBypassModel": null,
                "collisionPass": 0,
                "Lifespan": 0.0,
                "name": "AgeModel_Projectile",
                "ImplementationType": "Assets.Scripts.Simulation.Towers.Projectiles.Behaviors.Age, Assembly-CSharp, Version=0.0.0.0, Culture=neutral, PublicKeyToken=null"
              },
              {
                "assetId": "80178409df24b3b479342ed73cffb63d",
                "lifespan": 1.0,
                "useTowerPosition": true,
                "collisionPass": 0,
                "name": "CreateTextEffectModel_",
                "ImplementationType": "Assets.Scripts.Simulation.Towers.Projectiles.Behaviors.CreateTextEffect, Assembly-CSharp, Version=0.0.0.0, Culture=neutral, PublicKeyToken=null"
              },
              {
                "display": "ea93504240deadd41aed8f22737322c9",
                "layer": 0,
                "positionOffset": {
                  "x": 0.0,
                  "y": 0.0,
                  "z": 0.0,
                  "MagnitudeSquared": 0.0,
                  "Magnitude": 0.0,
                  "Rotation": 0.0,
                  "SimToDispRotation": 180.0
                },
                "scale": 1.0,
                "ignoreRotation": false,
                "animationChanges": null,
                "delayedReveal": 0.0,
                "name": "DisplayModel_ProjectileDisplay",
                "ImplementationType": "Assets.Scripts.Simulation.Behaviors.DisplayBehavior, Assembly-CSharp, Version=0.0.0.0, Culture=neutral, PublicKeyToken=null"
              }
            ],
            "collisionPasses": [
              0
            ],
            "canCollideWithBloons": true,
            "radius": 5.0,
            "vsBlockerRadius": 0.0,
            "hasDamageModifiers": false,
            "dontUseCollisionChecker": false,
            "checkCollisionFrames": 0,
            "ignoreNonTargetable": false,
            "ignorePierceExhaustion": false,
            "saveId": null,
            "CappedPierce": 9999999.0,
            "name": "ProjectileModel_Projectile",
            "ImplementationType": "Assets.Scripts.Simulation.Towers.Projectiles.Projectile, Assembly-CSharp, Version=0.0.0.0, Culture=neutral, PublicKeyToken=null"
          },
          "rateFrames": 2,
          "fireWithoutTarget": false,
          "fireBetweenRounds": false,
          "behaviors": [
            {
              "count": 18,
              "allowSpawnOnInitialise": false,
              "ignoreInSandbox": false,
              "name": "EmissionsPerRoundFilterModel_",
              "ImplementationType": "Assets.Scripts.Simulation.Towers.Weapons.Behaviors.EmissionsPerRoundFilter, Assembly-CSharp, Version=0.0.0.0, Culture=neutral, PublicKeyToken=null"
            },
            {
              "min": 0.05,
              "name": "WeaponRateMinModel_",
              "ImplementationType": "Assets.Scripts.Simulation.Towers.Weapons.Behaviors.WeaponRateMin, Assembly-CSharp, Version=0.0.0.0, Culture=neutral, PublicKeyToken=null"
            }
          ],
          "useAttackPosition": false,
          "startInCooldown": false,
          "customStartCooldown": 0.0,
          "customStartCooldownFrames": 0,
          "animateOnMainAttack": false,
          "Rate": 0.05,
          "name": "WeaponModel_Weapon",
          "ImplementationType": "Assets.Scripts.Simulation.Towers.Weapons.Weapon, Assembly-CSharp, Version=0.0.0.0, Culture=neutral, PublicKeyToken=null"
        }
      ],
      "behaviors": [
        {
          "minRadius": 0.0,
          "maxRadius": 1.0,
          "mapBorder": 7.0,
          "useTerrainHeight": false,
          "isOnSubTower": false,
          "name": "RandomPositionBasicModel_",
          "ImplementationType": "Assets.Scripts.Simulation.Towers.Behaviors.Attack.Behaviors.RandomPositionBasic, Assembly-CSharp, Version=0.0.0.0, Culture=neutral, PublicKeyToken=null"
        },
        {
          "filters": [
            {
              "isActive": true,
              "ignoreBroadPhase": false,
              "name": "FilterInvisibleModel_",
              "ImplementationType": "Assets.Scripts.Simulation.Towers.Filters.FilterInvisible, Assembly-CSharp, Version=0.0.0.0, Culture=neutral, PublicKeyToken=null"
            }
          ],
          "name": "AttackFilterModel_",
          "ImplementationType": "Assets.Scripts.Simulation.Towers.Behaviors.Attack.Behaviors.AttackFilter, Assembly-CSharp, Version=0.0.0.0, Culture=neutral, PublicKeyToken=null"
        }
      ],
      "range": 40.0,
      "targetProvider": {
        "minRadius": 20.0,
        "maxRadius": 40.0,
        "mapBorder": 7.0,
        "useTerrainHeight": false,
        "isOnSubTower": false,
        "name": "RandomPositionBasicModel_",
        "ImplementationType": "Assets.Scripts.Simulation.Towers.Behaviors.Attack.Behaviors.RandomPositionBasic, Assembly-CSharp, Version=0.0.0.0, Culture=neutral, PublicKeyToken=null"
      },
      "offsetX": 0.0,
      "offsetY": 0.0,
      "offsetZ": 0.0,
      "attackThroughWalls": true,
      "fireWithoutTarget": false,
      "framesBeforeRetarget": 0,
      "addsToSharedGrid": true,
      "sharedGridRange": 0.0,
      "name": "AttackModel_Attack_",
      "ImplementationType": "Assets.Scripts.Simulation.Towers.Behaviors.Attack.Attack, Assembly-CSharp, Version=0.0.0.0, Culture=neutral, PublicKeyToken=null"
    },
    {
      "multiplier": 1.1,
      "mutatorId": "CentralMarketBuff",
      "maxStackCount": 10,
      "buffLocsName": "CentralMarketBuff",
      "buffIconName": "BuffIconBananaFarmxx4",
      "maxStackSize": 10,
      "isGlobalRange": true,
      "name": "CentralMarketBuffModel_",
      "ImplementationType": "Assets.Scripts.Simulation.Towers.Behaviors.CentralMarketBuff, Assembly-CSharp, Version=0.0.0.0, Culture=neutral, PublicKeyToken=null"
    },
    {
      "cashPerRound": 4000.0,
      "cashRoundBonusMultiplier": 0.0,
      "lifespan": 1.0,
      "assetId": "80178409df24b3b479342ed73cffb63d",
      "distributeCash": false,
      "name": "",
      "ImplementationType": "Assets.Scripts.Simulation.Towers.Behaviors.PerRoundCashBonusTower, Assembly-CSharp, Version=0.0.0.0, Culture=neutral, PublicKeyToken=null"
    },
    {
      "amount": 10,
      "lifespan": 1.25,
      "assetId": "eb70b6823aec0644c81f873e94cb26cc",
      "name": "BonusLivesPerRoundModel_",
      "ImplementationType": "Assets.Scripts.Simulation.Towers.Behaviors.BonusLivesPerRound, Assembly-CSharp, Version=0.0.0.0, Culture=neutral, PublicKeyToken=null"
    },
    {
      "display": "d9eb899fd1dc7df48a3f45197426fd5d",
      "layer": -1,
      "positionOffset": {
        "x": 0.0,
        "y": 0.0,
        "z": 0.0,
        "MagnitudeSquared": 0.0,
        "Magnitude": 0.0,
        "Rotation": 0.0,
        "SimToDispRotation": 180.0
      },
      "scale": 1.0,
      "ignoreRotation": false,
      "animationChanges": null,
      "delayedReveal": 0.0,
      "name": "DisplayModel_TowerDisplay",
      "ImplementationType": "Assets.Scripts.Simulation.Behaviors.DisplayBehavior, Assembly-CSharp, Version=0.0.0.0, Culture=neutral, PublicKeyToken=null"
    }
  ],
  "footprint": {
    "xWidth": 30.0,
    "yWidth": 30.0,
    "doesntBlockTowerPlacement": false,
    "ignoresPlacementCheck": false,
    "ignoresTowerOverlap": false,
    "name": "RectangleFootprintModel_",
    "ImplementationType": "Assets.Scripts.Simulation.Towers.Behaviors.RectangleFootprint, Assembly-CSharp, Version=0.0.0.0, Culture=neutral, PublicKeyToken=null"
  },
  "dontDisplayUpgrades": false,
  "emoteSpriteSmall": null,
  "emoteSpriteLarge": null,
  "doesntRotate": true,
  "upgrades": [
    {
      "tower": "BananaFarm-205",
      "upgrade": "Greater Production"
    }
  ],
  "appliedUpgrades": [
    "EZ Collect",
    "Banana Salvage",
    "Marketplace",
    "Central Market",
    "Monkey Wall Street",
    "Increased Production"
  ],
  "targetTypes": null,
  "paragonUpgrade": null,
  "isSubTower": false,
  "isBakable": true,
  "powerName": null,
  "showPowerTowerBuffs": false,
  "animationSpeed": 1.0,
  "towerSelectionMenuThemeId": "BananaFarm",
  "ignoreCoopAreas": false,
  "canAlwaysBeSold": false,
  "isParagon": false,
  "sellbackModifierAdd": 0.1,
  "isPowerTower": false,
  "IsBaseTower": false,
  "TargetTypes": null,
  "name": "BananaFarm-105",
  "ImplementationType": "Assets.Scripts.Simulation.Towers.Tower, Assembly-CSharp, Version=0.0.0.0, Culture=neutral, PublicKeyToken=null"
}